vplm/__init__.py
vplm/models/__init__.py
vplm/models/vplm/__init__.py
vplm/models/vplm/configuration_transformer.py
vplm/models/vplm/modeling_transformer.py
vplm/models/vplm/tokenization_transformer.py
vplm/models/vplm/vocab.txt
vplm/utils/__init__.py
vplm/utils/pack_utils.py
vplm-0.0.1.dist-info/LICENSE
vplm-0.0.1.dist-info/METADATA
vplm-0.0.1.dist-info/WHEEL
vplm-0.0.1.dist-info/top_level.txt
vplm-0.0.1.dist-info/RECORD
