Metadata-Version: 2.2
Name: vplm
Version: 0.0.1
Summary: VenusPLM is a protein language model that designed for protein representation and protein design.
Home-page: https://github.com/ai4protein/VenusPLM
Author: Mingcheng Li
Author-email: lmc@mail.ecust.edu.cn
License: MIT License
Project-URL: Bug Tracker, https://github.com/ai4protein/VenusPLM/issues
Project-URL: Documentation, https://venusplm.readthedocs.io/
Project-URL: Source Code, https://github.com/ai4protein/VenusPLM
Classifier: Programming Language :: Python :: 3.10
Classifier: Programming Language :: Python :: 3.11
Classifier: Programming Language :: Python :: 3.12
Classifier: Programming Language :: Python :: 3.13
Classifier: Programming Language :: Python :: 3.14
Classifier: License :: OSI Approved :: MIT License
Classifier: Operating System :: OS Independent
Classifier: Development Status :: 3 - Alpha
Requires-Python: >=3.10
License-File: LICENSE
Requires-Dist: torch>=2.5.0
Requires-Dist: transformers
Requires-Dist: protobuf
Provides-Extra: dev
Requires-Dist: pytest>=6.0.0; extra == "dev"
Dynamic: author
Dynamic: author-email
Dynamic: classifier
Dynamic: description
Dynamic: description-content-type
Dynamic: home-page
Dynamic: license
Dynamic: project-url
Dynamic: provides-extra
Dynamic: requires-dist
Dynamic: requires-python
Dynamic: summary
